fw_gear_petsurfer_mc/__init__.py
fw_gear_petsurfer_mc/parser.py
fw_gear_petsurfer_mc/pet_utils.py
fw_gear_petsurfer_mc/util.py
fw_gear_petsurfer_mc-0.1.5.dist-info/LICENSE
fw_gear_petsurfer_mc-0.1.5.dist-info/METADATA
fw_gear_petsurfer_mc-0.1.5.dist-info/WHEEL
fw_gear_petsurfer_mc-0.1.5.dist-info/RECORD
