Metadata-Version: 2.1
Name: fw_gear_petsurfer_mc
Version: 0.1.5
Summary: 
Home-page: https://gitlab.com/flywheel-io/scientific-solutions/gears/petsurfer-mc
License: MIT
Keywords: Flywheel,Gears
Author: Flywheel
Author-email: support@flywheel.io
Requires-Python: >=3.10,<4.0
Classifier: License :: OSI Approved :: MIT License
Classifier: Programming Language :: Python :: 3
Classifier: Programming Language :: Python :: 3.10
Classifier: Programming Language :: Python :: 3.11
Classifier: Programming Language :: Python :: 3.12
Classifier: Topic :: Scientific/Engineering
Requires-Dist: flywheel-gear-toolkit (>=0.6,<0.7)
Requires-Dist: flywheel-sdk (>=19.3,<20.0)
Requires-Dist: fw-meta (==2.1.1)
Requires-Dist: matplotlib (>=3.6.2,<4.0.0)
Requires-Dist: nibabel (>=5.3.2,<6.0.0)
Requires-Dist: numpy (>=1.26.4,<2.0.0)
Requires-Dist: packaging (==20.4)
Requires-Dist: pandas (>=2.2.2,<3.0.0)
Requires-Dist: pytz (>=2022.6,<2023.0)
Requires-Dist: requests-toolbelt (>=1.0,<2.0)
Requires-Dist: seaborn (>=0.12.1,<0.13.0)
Project-URL: Repository, https://gitlab.com/flywheel-io/scientific-solutions/gears/petsurfer-mc
